cfn_encrypt/__init__.py
cfn_encrypt/get_ssm_value.py
cfn_encrypt/simple_encrypt.py
cfn_encrypt/ssm_parameter.py
cfn_encrypt-0.0.14.dist-info/DESCRIPTION.rst
cfn_encrypt-0.0.14.dist-info/METADATA
cfn_encrypt-0.0.14.dist-info/RECORD
cfn_encrypt-0.0.14.dist-info/WHEEL
cfn_encrypt-0.0.14.dist-info/metadata.json
cfn_encrypt-0.0.14.dist-info/top_level.txt
