Metadata-Version: 2.0
Name: cfn-encrypt
Version: 0.0.14
Summary: Lambda cloudformation custom resource that use KMS encrypt
Home-page: https://github.com/nordcloud/cfn-encrypt
Author: Martin Kaberg
Author-email: martin.kaberg@nordcloud.com
License: Apache Common 2.0
Platform: UNKNOWN
Requires-Dist: awacs (>=0.7.0)
Requires-Dist: troposphere (>=1.9.5)
